{
  "time": 1709390020934,
  "blocks": [
    {
      "id": "oxRrS24aRO",
      "type": "header",
      "data": {
        "text": "This is Bikram",
        "level": 2
      }
    },
    {
      "id": "_Xwe_mZL0E",
      "type": "paragraph",
      "data": {
        "text": "Welcome to my page"
      }
    },
    {
      "id": "wsA2PTNu2b",
      "type": "paragraph",
      "data": {
        "text": "And welcome!"
      }
    },
    {
      "id": "JRiEzszdVP",
      "type": "paragraph",
      "data": {
        "text": "And some changed file again!"
      }
    },
    {
      "id": "15gFKasRUG",
      "type": "paragraph",
      "data": {
        "text": "Updated"
      }
    }
  ],
  "version": "2.29.0"
}